sample/__init__.py
sample/package_data.dat
sivasample-0.2.0.data/data/my_data/data_file
sivasample-0.2.0.dist-info/DESCRIPTION.rst
sivasample-0.2.0.dist-info/METADATA
sivasample-0.2.0.dist-info/RECORD
sivasample-0.2.0.dist-info/WHEEL
sivasample-0.2.0.dist-info/entry_points.txt
sivasample-0.2.0.dist-info/metadata.json
sivasample-0.2.0.dist-info/top_level.txt
